pkgdemo/add.py
pkgdemo_munzii-0.1.dist-info/METADATA
pkgdemo_munzii-0.1.dist-info/WHEEL
pkgdemo_munzii-0.1.dist-info/top_level.txt
pkgdemo_munzii-0.1.dist-info/RECORD
