Metadata-Version: 2.1
Name: pkgdemo-munzii
Version: 0.1
Summary: demo execution
Home-page: UNKNOWN
Author: munziiliu
Author-email: UNKNOWN
License: 549099743@qq.com
Platform: UNKNOWN
